balcony/__init__.py
balcony/__main__.py
balcony/aws.py
balcony/boto3_data_export.py
balcony/botocore_utils.py
balcony/cli.py
balcony/config.py
balcony/custom_nodes/__init__.py
balcony/custom_nodes/codebuild.py
balcony/custom_nodes/ecs.py
balcony/custom_nodes/iam.py
balcony/custom_nodes/lambda_functions.py
balcony/custom_nodes/s3.py
balcony/custom_nodes/ses.py
balcony/custom_nodes/sqs.py
balcony/custom_nodes/ssm.py
balcony/custom_tf_import_configs/dynamodb.yaml
balcony/custom_tf_import_configs/ec2.yaml
balcony/custom_tf_import_configs/ecs.yaml
balcony/custom_tf_import_configs/elasticache.yaml
balcony/custom_tf_import_configs/elbv2.yaml
balcony/custom_tf_import_configs/iam.yaml
balcony/custom_tf_import_configs/lambda.yaml
balcony/custom_tf_import_configs/rds.yaml
balcony/custom_tf_import_configs/s3.yaml
balcony/custom_tf_import_configs/sns.yaml
balcony/custom_tf_import_configs/sqs.yaml
balcony/custom_tf_import_configs/vpc.yaml
balcony/custom_yamls/_example_service.yaml
balcony/custom_yamls/dynamodb.yaml
balcony/custom_yamls/ec2.yaml
balcony/custom_yamls/ecs.yaml
balcony/custom_yamls/elbv2.yaml
balcony/custom_yamls/iam.yaml
balcony/custom_yamls/s3.yaml
balcony/custom_yamls/sqs.yaml
balcony/errors.py
balcony/nodes.py
balcony/reader.py
balcony/registries.py
balcony/relations.py
balcony/terraform_import/__init__.py
balcony/terraform_import/importer.py
balcony/terraform_import/models.py
balcony/terraform_import/parsers.py
balcony/terraform_import/wizard.py
balcony/test.py
balcony/utils.py
balcony/yaml_config.py
balcony/yaml_validators.py
balcony-0.3.10.dist-info/WHEEL
balcony-0.3.10.dist-info/entry_points.txt
balcony-0.3.10.dist-info/METADATA
balcony-0.3.10.dist-info/RECORD
