Metadata-Version: 2.4
Name: balcony
Version: 0.3.10
Summary: Read any resource in your AWS Account. You can generate terraform code for them, too.
Author: Oguzhan Yilmaz
Author-email: Oguzhan Yilmaz <oguzhanylmz271@gmail.com>
License-Expression: Apache-2.0
Requires-Dist: aws-jmespath-utils>=1.1.0
Requires-Dist: boto3>=1.42.9
Requires-Dist: inflect>=7.5.0
Requires-Dist: jinja2<4
Requires-Dist: mkdocs-autorefs>=1.4.3
Requires-Dist: mkdocs-material>=9.7.0
Requires-Dist: mkdocstrings>=1.0.0
Requires-Dist: pydantic<2
Requires-Dist: pyyaml>=6.0.3
Requires-Dist: typer>=0.20.0
Requires-Python: >=3.12
Project-URL: Documentation, https://oguzhan-yilmaz.github.io/balcony/
Project-URL: Github, https://github.com/oguzhan-yilmaz/balcony
Project-URL: Releases, https://github.com/oguzhan-yilmaz/balcony/releases
Project-URL: aws-jmespath-utils, https://github.com/oguzhan-yilmaz/aws-jmespath-utils
